beets_beatport4-0.4.1.dist-info/licenses/LICENSE
beetsplug/__init__.py
beetsplug/beatport4.py
beets_beatport4-0.4.1.dist-info/METADATA
beets_beatport4-0.4.1.dist-info/WHEEL
beets_beatport4-0.4.1.dist-info/top_level.txt
beets_beatport4-0.4.1.dist-info/RECORD
