Metadata-Version: 2.4
Name: beets-beatport4
Version: 0.4.1
Summary: Plugin for beets (http://beets.io) to replace stock beatport plugin which is not yet compatible with Beatport API v4.
Author-email: Szymon 'Samik' Tarasinski <st.samik@gmail.com>
License-Expression: MIT
Project-URL: Homepage, https://github.com/Samik081/beets-beatport4
Project-URL: Download, https://github.com/Samik081/beets-beatport4/releases/download/v0.4.1/beets-beatport4-0.4.1.tar.gz
Classifier: Topic :: Multimedia :: Sound/Audio
Classifier: Topic :: Multimedia :: Sound/Audio :: Players :: MP3
Classifier: Environment :: Console
Classifier: Environment :: Web Environment
Classifier: Programming Language :: Python
Classifier: Programming Language :: Python :: 3
Classifier: Programming Language :: Python :: 3.6
Classifier: Programming Language :: Python :: 3.7
Classifier: Programming Language :: Python :: 3.8
Classifier: Programming Language :: Python :: 3.9
Classifier: Programming Language :: Python :: 3.10
Classifier: Programming Language :: Python :: 3.11
Classifier: Programming Language :: Python :: 3.12
Requires-Python: >=3.6
License-File: LICENSE
Requires-Dist: beets>=2.5.1
Requires-Dist: requests
Requires-Dist: confuse
Provides-Extra: dev
Requires-Dist: mypy; extra == "dev"
Requires-Dist: types-requests; extra == "dev"
Dynamic: license-file
